qcc/__init__.py
qcc/__main__.py
qcc/cli/__init__.py
qcc/cli/api.py
qcc/cli/auth.py
qcc/cli/codes.py
qcc/cli/manage.py
qcc/cli/session.py
qcc/cli/static.py
qcc/cli/status.py
qcc/cli/utils.py
qcc/client.py
qcc/conf.py
qcc/endpoints/__init__.py
qcc/endpoints/auth.py
qcc/endpoints/base.py
qcc/endpoints/dynamic.py
qcc/endpoints/manage.py
qcc/endpoints/static.py
qcc/exceptions.py
qcc/http.py
qcc/models.py
qualicharge_client-0.3.0.dist-info/LICENSE
qualicharge_client-0.3.0.dist-info/METADATA
qualicharge_client-0.3.0.dist-info/WHEEL
qualicharge_client-0.3.0.dist-info/entry_points.txt
qualicharge_client-0.3.0.dist-info/RECORD
